_hpsm.cpython-310-aarch64-linux-gnu.so
_winnowing.cpython-310-aarch64-linux-gnu.so
scanoss_winnowing-0.7.0.dist-info/WHEEL
scanoss_winnowing-0.7.0.dist-info/top_level.txt
scanoss_winnowing-0.7.0.dist-info/METADATA
scanoss_winnowing-0.7.0.dist-info/RECORD
scanoss_winnowing-0.7.0.dist-info/licenses/LICENSE
scanoss_winnowing/_winnowing.c
scanoss_winnowing/scanossbase.py
scanoss_winnowing/header_filter.py
scanoss_winnowing/winnowing.py
scanoss_winnowing/__init__.py
scanoss_winnowing/_hpsm.c
