Metadata-Version: 2.4
Name: scanoss-winnowing
Version: 0.7.0
Summary: Python Library implementing a C version of the SCANOSS Winnowing algorithm
Home-page: https://scanoss.com
Author: SCANOSS
Author-email: SCANOSS <info@scanoss.com>
License: MIT
Project-URL: Source, https://github.com/scanoss/scanoss-winnowing.py
Project-URL: Tracker, https://github.com/scanoss/scanoss-winnowing.py/issues
Classifier: Programming Language :: Python :: 3
Classifier: Programming Language :: C
Classifier: License :: OSI Approved :: MIT License
Classifier: Development Status :: 5 - Production/Stable
Classifier: Operating System :: POSIX :: Linux
Classifier: Operating System :: MacOS :: MacOS X
Classifier: Operating System :: Microsoft :: Windows
Requires-Python: >=3.9
License-File: LICENSE
Requires-Dist: crc32c>=2.2
Requires-Dist: binaryornot
Dynamic: license-file
